mongoclass/__init__.py
mongoclass/cache.py
mongoclass/client.py
mongoclass/cursor.py
tests/mongita/__init__.py
tests/mongita/test_basic.py
tests/mongita/test_count.py
tests/mongita/test_cursor.py
tests/mongita/test_delete.py
tests/mongita/test_find.py
tests/mongita/test_insert.py
tests/mongita/test_update.py
tests/mongoclass/__init__.py
tests/mongoclass/test_collection.py
tests/mongoclass/test_find.py
tests/mongoclass/test_has.py
tests/mongoclass/test_id.py
tests/mongoclass/test_index.py
tests/mongoclass/test_is_testing.py
tests/mongoclass/test_one.py
tests/mongoclass/test_rm.py
tests/pymongo/__init__.py
tests/pymongo/test_basic.py
tests/pymongo/test_count.py
tests/pymongo/test_cursor.py
tests/pymongo/test_delete.py
tests/pymongo/test_find.py
tests/pymongo/test_insert.py
tests/pymongo/test_update.py
venv/bin/activate_this.py
venv/bin/jsonpath.py
venv/bin/rst2html.py
venv/bin/rst2html4.py
venv/bin/rst2html5.py
venv/bin/rst2latex.py
venv/bin/rst2man.py
venv/bin/rst2odt.py
venv/bin/rst2odt_prepstyles.py
venv/bin/rst2pseudoxml.py
venv/bin/rst2s5.py
venv/bin/rst2xetex.py
venv/bin/rst2xml.py
venv/bin/rstpep2html.py
venv/etc/pyflyby/canonical.py
venv/etc/pyflyby/common.py
venv/etc/pyflyby/forget.py
venv/etc/pyflyby/mandatory.py
venv/etc/pyflyby/numpy.py
venv/etc/pyflyby/std.py
python_mongoclass-0.1.30.dist-info/LICENSE
python_mongoclass-0.1.30.dist-info/METADATA
python_mongoclass-0.1.30.dist-info/WHEEL
python_mongoclass-0.1.30.dist-info/top_level.txt
python_mongoclass-0.1.30.dist-info/RECORD
