Metadata-Version: 2.1
Name: python-mongoclass
Version: 0.1.30
Summary: mongoclass
License: MIT
Requires-Python: >=3.9
License-File: LICENSE
Requires-Dist: dnspython <3,>=2.2.1
Requires-Dist: furl <3,>=2.1.3
Requires-Dist: mongita <2,>=1.1.1
Requires-Dist: pymongo <5,>=4.5.0
Requires-Dist: redis <6,>=5.0.0
Requires-Dist: requests <3,>=2.31.0
Requires-Dist: rich <14,>=13.5.2
Provides-Extra: dev
Requires-Dist: icecream ; extra == 'dev'
Requires-Dist: ipython ; extra == 'dev'
Requires-Dist: ipython-suggestions ; extra == 'dev'
Requires-Dist: restmagic ; extra == 'dev'
Requires-Dist: mypy ; extra == 'dev'
Requires-Dist: pip-tools ; extra == 'dev'
Requires-Dist: pyflyby ; extra == 'dev'
Requires-Dist: twine ; extra == 'dev'
Provides-Extra: tests
Requires-Dist: coverage[toml] <7,>=6 ; extra == 'tests'
Requires-Dist: pytest <8,>=7 ; extra == 'tests'
Requires-Dist: pytest-cov <5,>=4 ; extra == 'tests'
Requires-Dist: pytest-doctestplus <1,>=0.13 ; extra == 'tests'
Requires-Dist: pytest-lazy-fixture ~=0.6.3 ; extra == 'tests'
Requires-Dist: pytest-mock <4,>=3 ; extra == 'tests'
Requires-Dist: pytest-remotedata <1,>=0.4.0 ; extra == 'tests'
Requires-Dist: pytest-sugar <1,>=0.9.7 ; extra == 'tests'
Requires-Dist: pytest-xdist <3,>=2 ; extra == 'tests'
Requires-Dist: tox <5,>=4.6.4 ; extra == 'tests'
